miumapp/__init__.py
miumapp/demo.html
miumapp/demo.py
miumapp-1.0.11.dist-info/LICENSE
miumapp-1.0.11.dist-info/WHEEL
miumapp-1.0.11.dist-info/METADATA
miumapp-1.0.11.dist-info/RECORD
