Metadata-Version: 2.1
Name: miumapp
Version: 1.0.11
Summary: 一个使用 Python + HTML 开发桌面 GUI 应用的框架，支持 Windows、Mac、Linux 平台。
Keywords: electron,flutter,uniapp,pyqt5,miumapp
Author-email: 江南雨上 <lcctoor@outlook.com>
Classifier: License :: OSI Approved :: Apache Software License
Requires-Dist: arts>=2024.7.29
Project-URL: Source, https://github.com/lcctoor/arts/tree/main/arts/miumapp
